{
    "data": {
        "img": "/data/local-files?d=industry_safety_0/rgb_04979_3.jpg"
    },
    "predictions": [
        {
            "result": [
                {
                    "original_width": 640,
                    "original_height": 360,
                    "image_rotation": 0,
                    "value": {
                        "x": 52.17854022979736,
                        "y": 21.825260586208767,
                        "width": 0.22471910112359553,
                        "keypointlabels": [
                            "nose"
                        ]
                    },
                    "from_name": "kp-1",
                    "to_name": "img-1",
                    "type": "keypointlabels",
                    "origin": "manual"
                },
                {
                    "original_width": 640,
                    "original_height": 360,
                    "image_rotation": 0,
                    "value": {
                        "x": 51.359124183654785,
                        "y": 23.933558993869358,
                        "width": 0.22471910112359553,
                        "keypointlabels": [
                            "left_shoulder"
                        ]
                    },
                    "from_name": "kp-1",
                    "to_name": "img-1",
                    "type": "keypointlabels",
                    "origin": "manual"
                },
                {
                    "original_width": 640,
                    "original_height": 360,
                    "image_rotation": 0,
                    "value": {
                        "x": 47.220869064331055,
                        "y": 27.27227105034722,
                        "width": 0.22471910112359553,
                        "keypointlabels": [
                            "right_shoulder"
                        ]
                    },
                    "from_name": "kp-1",
                    "to_name": "img-1",
                    "type": "keypointlabels",
                    "origin": "manual"
                },
                {
                    "original_width": 640,
                    "original_height": 360,
                    "image_rotation": 0,
                    "value": {
                        "x": 51.91659450531006,
                        "y": 30.881614685058594,
                        "width": 0.22471910112359553,
                        "keypointlabels": [
                            "left_elbow"
                        ]
                    },
                    "from_name": "kp-1",
                    "to_name": "img-1",
                    "type": "keypointlabels",
                    "origin": "manual"
                },
                {
                    "original_width": 640,
                    "original_height": 360,
                    "image_rotation": 0,
                    "value": {
                        "x": 45.909013748168945,
                        "y": 37.17947642008463,
                        "width": 0.22471910112359553,
                        "keypointlabels": [
                            "right_elbow"
                        ]
                    },
                    "from_name": "kp-1",
                    "to_name": "img-1",
                    "type": "keypointlabels",
                    "origin": "manual"
                },
                {
                    "original_width": 640,
                    "original_height": 360,
                    "image_rotation": 0,
                    "value": {
                        "x": 54.51328754425049,
                        "y": 34.50098673502604,
                        "width": 0.22471910112359553,
                        "keypointlabels": [
                            "left_wrist"
                        ]
                    },
                    "from_name": "kp-1",
                    "to_name": "img-1",
                    "type": "keypointlabels",
                    "origin": "manual"
                },
                {
                    "original_width": 640,
                    "original_height": 360,
                    "image_rotation": 0,
                    "value": {
                        "x": 49.06733512878418,
                        "y": 42.07789950900607,
                        "width": 0.22471910112359553,
                        "keypointlabels": [
                            "right_wrist"
                        ]
                    },
                    "from_name": "kp-1",
                    "to_name": "img-1",
                    "type": "keypointlabels",
                    "origin": "manual"
                },
                {
                    "original_width": 640,
                    "original_height": 360,
                    "image_rotation": 0,
                    "value": {
                        "x": 51.1599063873291,
                        "y": 40.440330505371094,
                        "width": 0.22471910112359553,
                        "keypointlabels": [
                            "left_hip"
                        ]
                    },
                    "from_name": "kp-1",
                    "to_name": "img-1",
                    "type": "keypointlabels",
                    "origin": "manual"
                },
                {
                    "original_width": 640,
                    "original_height": 360,
                    "image_rotation": 0,
                    "value": {
                        "x": 48.47771167755127,
                        "y": 42.30224609375,
                        "width": 0.22471910112359553,
                        "keypointlabels": [
                            "right_hip"
                        ]
                    },
                    "from_name": "kp-1",
                    "to_name": "img-1",
                    "type": "keypointlabels",
                    "origin": "manual"
                },
                {
                    "original_width": 640,
                    "original_height": 360,
                    "image_rotation": 0,
                    "value": {
                        "x": 50.695319175720215,
                        "y": 48.34000481499566,
                        "width": 0.22471910112359553,
                        "keypointlabels": [
                            "left_knee"
                        ]
                    },
                    "from_name": "kp-1",
                    "to_name": "img-1",
                    "type": "keypointlabels",
                    "origin": "manual"
                },
                {
                    "original_width": 640,
                    "original_height": 360,
                    "image_rotation": 0,
                    "value": {
                        "x": 48.60508441925049,
                        "y": 50.14533572726779,
                        "width": 0.22471910112359553,
                        "keypointlabels": [
                            "right_knee"
                        ]
                    },
                    "from_name": "kp-1",
                    "to_name": "img-1",
                    "type": "keypointlabels",
                    "origin": "manual"
                },
                {
                    "original_width": 640,
                    "original_height": 360,
                    "image_rotation": 0,
                    "value": {
                        "x": 49.6736478805542,
                        "y": 55.46749962700738,
                        "width": 0.22471910112359553,
                        "keypointlabels": [
                            "left_ankle"
                        ]
                    },
                    "from_name": "kp-1",
                    "to_name": "img-1",
                    "type": "keypointlabels",
                    "origin": "manual"
                },
                {
                    "original_width": 640,
                    "original_height": 360,
                    "image_rotation": 0,
                    "value": {
                        "x": 48.66934776306152,
                        "y": 58.11592102050781,
                        "width": 0.22471910112359553,
                        "keypointlabels": [
                            "right_ankle"
                        ]
                    },
                    "from_name": "kp-1",
                    "to_name": "img-1",
                    "type": "keypointlabels",
                    "origin": "manual"
                },
                {
                    "original_width": 640,
                    "original_height": 360,
                    "image_rotation": 0,
                    "value": {
                        "x": 44.53125,
                        "y": 11.11111111111111,
                        "width": 12.34375,
                        "height": 51.666666666666664,
                        "rectanglelabels": [
                            "People"
                        ]
                    },
                    "from_name": "label",
                    "to_name": "img-1",
                    "type": "rectanglelabels",
                    "origin": "manual"
                },
                {
                    "original_width": 640,
                    "original_height": 360,
                    "image_rotation": 0,
                    "value": {
                        "x": 0.0,
                        "y": 0.0,
                        "width": 0.22471910112359553,
                        "keypointlabels": [
                            "nose"
                        ]
                    },
                    "from_name": "kp-1",
                    "to_name": "img-1",
                    "type": "keypointlabels",
                    "origin": "manual"
                },
                {
                    "original_width": 640,
                    "original_height": 360,
                    "image_rotation": 0,
                    "value": {
                        "x": 0.0,
                        "y": 0.0,
                        "width": 0.22471910112359553,
                        "keypointlabels": [
                            "left_shoulder"
                        ]
                    },
                    "from_name": "kp-1",
                    "to_name": "img-1",
                    "type": "keypointlabels",
                    "origin": "manual"
                },
                {
                    "original_width": 640,
                    "original_height": 360,
                    "image_rotation": 0,
                    "value": {
                        "x": 0.0,
                        "y": 0.0,
                        "width": 0.22471910112359553,
                        "keypointlabels": [
                            "right_shoulder"
                        ]
                    },
                    "from_name": "kp-1",
                    "to_name": "img-1",
                    "type": "keypointlabels",
                    "origin": "manual"
                },
                {
                    "original_width": 640,
                    "original_height": 360,
                    "image_rotation": 0,
                    "value": {
                        "x": 0.0,
                        "y": 0.0,
                        "width": 0.22471910112359553,
                        "keypointlabels": [
                            "left_elbow"
                        ]
                    },
                    "from_name": "kp-1",
                    "to_name": "img-1",
                    "type": "keypointlabels",
                    "origin": "manual"
                },
                {
                    "original_width": 640,
                    "original_height": 360,
                    "image_rotation": 0,
                    "value": {
                        "x": 47.15754508972168,
                        "y": 100.0,
                        "width": 0.22471910112359553,
                        "keypointlabels": [
                            "right_elbow"
                        ]
                    },
                    "from_name": "kp-1",
                    "to_name": "img-1",
                    "type": "keypointlabels",
                    "origin": "manual"
                },
                {
                    "original_width": 640,
                    "original_height": 360,
                    "image_rotation": 0,
                    "value": {
                        "x": 0.0,
                        "y": 0.0,
                        "width": 0.22471910112359553,
                        "keypointlabels": [
                            "left_wrist"
                        ]
                    },
                    "from_name": "kp-1",
                    "to_name": "img-1",
                    "type": "keypointlabels",
                    "origin": "manual"
                },
                {
                    "original_width": 640,
                    "original_height": 360,
                    "image_rotation": 0,
                    "value": {
                        "x": 46.1789608001709,
                        "y": 98.41611226399739,
                        "width": 0.22471910112359553,
                        "keypointlabels": [
                            "right_wrist"
                        ]
                    },
                    "from_name": "kp-1",
                    "to_name": "img-1",
                    "type": "keypointlabels",
                    "origin": "manual"
                },
                {
                    "original_width": 640,
                    "original_height": 360,
                    "image_rotation": 0,
                    "value": {
                        "x": 0.0,
                        "y": 0.0,
                        "width": 0.22471910112359553,
                        "keypointlabels": [
                            "left_hip"
                        ]
                    },
                    "from_name": "kp-1",
                    "to_name": "img-1",
                    "type": "keypointlabels",
                    "origin": "manual"
                },
                {
                    "original_width": 640,
                    "original_height": 360,
                    "image_rotation": 0,
                    "value": {
                        "x": 0.0,
                        "y": 0.0,
                        "width": 0.22471910112359553,
                        "keypointlabels": [
                            "right_hip"
                        ]
                    },
                    "from_name": "kp-1",
                    "to_name": "img-1",
                    "type": "keypointlabels",
                    "origin": "manual"
                },
                {
                    "original_width": 640,
                    "original_height": 360,
                    "image_rotation": 0,
                    "value": {
                        "x": 0.0,
                        "y": 0.0,
                        "width": 0.22471910112359553,
                        "keypointlabels": [
                            "left_knee"
                        ]
                    },
                    "from_name": "kp-1",
                    "to_name": "img-1",
                    "type": "keypointlabels",
                    "origin": "manual"
                },
                {
                    "original_width": 640,
                    "original_height": 360,
                    "image_rotation": 0,
                    "value": {
                        "x": 0.0,
                        "y": 0.0,
                        "width": 0.22471910112359553,
                        "keypointlabels": [
                            "right_knee"
                        ]
                    },
                    "from_name": "kp-1",
                    "to_name": "img-1",
                    "type": "keypointlabels",
                    "origin": "manual"
                },
                {
                    "original_width": 640,
                    "original_height": 360,
                    "image_rotation": 0,
                    "value": {
                        "x": 0.0,
                        "y": 0.0,
                        "width": 0.22471910112359553,
                        "keypointlabels": [
                            "left_ankle"
                        ]
                    },
                    "from_name": "kp-1",
                    "to_name": "img-1",
                    "type": "keypointlabels",
                    "origin": "manual"
                },
                {
                    "original_width": 640,
                    "original_height": 360,
                    "image_rotation": 0,
                    "value": {
                        "x": 0.0,
                        "y": 0.0,
                        "width": 0.22471910112359553,
                        "keypointlabels": [
                            "right_ankle"
                        ]
                    },
                    "from_name": "kp-1",
                    "to_name": "img-1",
                    "type": "keypointlabels",
                    "origin": "manual"
                },
                {
                    "original_width": 640,
                    "original_height": 360,
                    "image_rotation": 0,
                    "value": {
                        "x": 35.78125,
                        "y": 86.38888888888889,
                        "width": 13.90625,
                        "height": 13.333333333333332,
                        "rectanglelabels": [
                            "People"
                        ]
                    },
                    "from_name": "label",
                    "to_name": "img-1",
                    "type": "rectanglelabels",
                    "origin": "manual"
                },
                {
                    "original_width": 640,
                    "original_height": 360,
                    "image_rotation": 0,
                    "value": {
                        "x": 0.0,
                        "y": 0.0,
                        "width": 0.22471910112359553,
                        "keypointlabels": [
                            "nose"
                        ]
                    },
                    "from_name": "kp-1",
                    "to_name": "img-1",
                    "type": "keypointlabels",
                    "origin": "manual"
                },
                {
                    "original_width": 640,
                    "original_height": 360,
                    "image_rotation": 0,
                    "value": {
                        "x": 72.41170883178711,
                        "y": 36.53867933485243,
                        "width": 0.22471910112359553,
                        "keypointlabels": [
                            "left_shoulder"
                        ]
                    },
                    "from_name": "kp-1",
                    "to_name": "img-1",
                    "type": "keypointlabels",
                    "origin": "manual"
                },
                {
                    "original_width": 640,
                    "original_height": 360,
                    "image_rotation": 0,
                    "value": {
                        "x": 66.51971340179443,
                        "y": 36.87242719862196,
                        "width": 0.22471910112359553,
                        "keypointlabels": [
                            "right_shoulder"
                        ]
                    },
                    "from_name": "kp-1",
                    "to_name": "img-1",
                    "type": "keypointlabels",
                    "origin": "manual"
                },
                {
                    "original_width": 640,
                    "original_height": 360,
                    "image_rotation": 0,
                    "value": {
                        "x": 0.0,
                        "y": 0.0,
                        "width": 0.22471910112359553,
                        "keypointlabels": [
                            "left_elbow"
                        ]
                    },
                    "from_name": "kp-1",
                    "to_name": "img-1",
                    "type": "keypointlabels",
                    "origin": "manual"
                },
                {
                    "original_width": 640,
                    "original_height": 360,
                    "image_rotation": 0,
                    "value": {
                        "x": 65.02155303955078,
                        "y": 44.058028327094185,
                        "width": 0.22471910112359553,
                        "keypointlabels": [
                            "right_elbow"
                        ]
                    },
                    "from_name": "kp-1",
                    "to_name": "img-1",
                    "type": "keypointlabels",
                    "origin": "manual"
                },
                {
                    "original_width": 640,
                    "original_height": 360,
                    "image_rotation": 0,
                    "value": {
                        "x": 0.0,
                        "y": 0.0,
                        "width": 0.22471910112359553,
                        "keypointlabels": [
                            "left_wrist"
                        ]
                    },
                    "from_name": "kp-1",
                    "to_name": "img-1",
                    "type": "keypointlabels",
                    "origin": "manual"
                },
                {
                    "original_width": 640,
                    "original_height": 360,
                    "image_rotation": 0,
                    "value": {
                        "x": 0.0,
                        "y": 0.0,
                        "width": 0.22471910112359553,
                        "keypointlabels": [
                            "right_wrist"
                        ]
                    },
                    "from_name": "kp-1",
                    "to_name": "img-1",
                    "type": "keypointlabels",
                    "origin": "manual"
                },
                {
                    "original_width": 640,
                    "original_height": 360,
                    "image_rotation": 0,
                    "value": {
                        "x": 67.97373294830322,
                        "y": 34.03839535183376,
                        "width": 0.22471910112359553,
                        "keypointlabels": [
                            "left_hip"
                        ]
                    },
                    "from_name": "kp-1",
                    "to_name": "img-1",
                    "type": "keypointlabels",
                    "origin": "manual"
                },
                {
                    "original_width": 640,
                    "original_height": 360,
                    "image_rotation": 0,
                    "value": {
                        "x": 63.69717597961426,
                        "y": 33.78843519422743,
                        "width": 0.22471910112359553,
                        "keypointlabels": [
                            "right_hip"
                        ]
                    },
                    "from_name": "kp-1",
                    "to_name": "img-1",
                    "type": "keypointlabels",
                    "origin": "manual"
                },
                {
                    "original_width": 640,
                    "original_height": 360,
                    "image_rotation": 0,
                    "value": {
                        "x": 0.0,
                        "y": 0.0,
                        "width": 0.22471910112359553,
                        "keypointlabels": [
                            "left_knee"
                        ]
                    },
                    "from_name": "kp-1",
                    "to_name": "img-1",
                    "type": "keypointlabels",
                    "origin": "manual"
                },
                {
                    "original_width": 640,
                    "original_height": 360,
                    "image_rotation": 0,
                    "value": {
                        "x": 63.53339195251465,
                        "y": 46.343163384331596,
                        "width": 0.22471910112359553,
                        "keypointlabels": [
                            "right_knee"
                        ]
                    },
                    "from_name": "kp-1",
                    "to_name": "img-1",
                    "type": "keypointlabels",
                    "origin": "manual"
                },
                {
                    "original_width": 640,
                    "original_height": 360,
                    "image_rotation": 0,
                    "value": {
                        "x": 0.0,
                        "y": 0.0,
                        "width": 0.22471910112359553,
                        "keypointlabels": [
                            "left_ankle"
                        ]
                    },
                    "from_name": "kp-1",
                    "to_name": "img-1",
                    "type": "keypointlabels",
                    "origin": "manual"
                },
                {
                    "original_width": 640,
                    "original_height": 360,
                    "image_rotation": 0,
                    "value": {
                        "x": 0.0,
                        "y": 0.0,
                        "width": 0.22471910112359553,
                        "keypointlabels": [
                            "right_ankle"
                        ]
                    },
                    "from_name": "kp-1",
                    "to_name": "img-1",
                    "type": "keypointlabels",
                    "origin": "manual"
                },
                {
                    "original_width": 640,
                    "original_height": 360,
                    "image_rotation": 0,
                    "value": {
                        "x": 61.25,
                        "y": 28.61111111111111,
                        "width": 12.65625,
                        "height": 24.444444444444443,
                        "rectanglelabels": [
                            "People"
                        ]
                    },
                    "from_name": "label",
                    "to_name": "img-1",
                    "type": "rectanglelabels",
                    "origin": "manual"
                },
                {
                    "original_width": 640,
                    "original_height": 360,
                    "image_rotation": 0,
                    "value": {
                        "x": 0.0,
                        "y": 0.0,
                        "width": 0.22471910112359553,
                        "keypointlabels": [
                            "nose"
                        ]
                    },
                    "from_name": "kp-1",
                    "to_name": "img-1",
                    "type": "keypointlabels",
                    "origin": "manual"
                },
                {
                    "original_width": 640,
                    "original_height": 360,
                    "image_rotation": 0,
                    "value": {
                        "x": 0.0,
                        "y": 0.0,
                        "width": 0.22471910112359553,
                        "keypointlabels": [
                            "left_shoulder"
                        ]
                    },
                    "from_name": "kp-1",
                    "to_name": "img-1",
                    "type": "keypointlabels",
                    "origin": "manual"
                },
                {
                    "original_width": 640,
                    "original_height": 360,
                    "image_rotation": 0,
                    "value": {
                        "x": 45.78845500946045,
                        "y": 20.96679475572374,
                        "width": 0.22471910112359553,
                        "keypointlabels": [
                            "right_shoulder"
                        ]
                    },
                    "from_name": "kp-1",
                    "to_name": "img-1",
                    "type": "keypointlabels",
                    "origin": "manual"
                },
                {
                    "original_width": 640,
                    "original_height": 360,
                    "image_rotation": 0,
                    "value": {
                        "x": 0.0,
                        "y": 0.0,
                        "width": 0.22471910112359553,
                        "keypointlabels": [
                            "left_elbow"
                        ]
                    },
                    "from_name": "kp-1",
                    "to_name": "img-1",
                    "type": "keypointlabels",
                    "origin": "manual"
                },
                {
                    "original_width": 640,
                    "original_height": 360,
                    "image_rotation": 0,
                    "value": {
                        "x": 44.86494064331055,
                        "y": 28.47832573784722,
                        "width": 0.22471910112359553,
                        "keypointlabels": [
                            "right_elbow"
                        ]
                    },
                    "from_name": "kp-1",
                    "to_name": "img-1",
                    "type": "keypointlabels",
                    "origin": "manual"
                },
                {
                    "original_width": 640,
                    "original_height": 360,
                    "image_rotation": 0,
                    "value": {
                        "x": 0.0,
                        "y": 0.0,
                        "width": 0.22471910112359553,
                        "keypointlabels": [
                            "left_wrist"
                        ]
                    },
                    "from_name": "kp-1",
                    "to_name": "img-1",
                    "type": "keypointlabels",
                    "origin": "manual"
                },
                {
                    "original_width": 640,
                    "original_height": 360,
                    "image_rotation": 0,
                    "value": {
                        "x": 45.282044410705566,
                        "y": 33.825437757703995,
                        "width": 0.22471910112359553,
                        "keypointlabels": [
                            "right_wrist"
                        ]
                    },
                    "from_name": "kp-1",
                    "to_name": "img-1",
                    "type": "keypointlabels",
                    "origin": "manual"
                },
                {
                    "original_width": 640,
                    "original_height": 360,
                    "image_rotation": 0,
                    "value": {
                        "x": 47.534003257751465,
                        "y": 33.09491475423177,
                        "width": 0.22471910112359553,
                        "keypointlabels": [
                            "left_hip"
                        ]
                    },
                    "from_name": "kp-1",
                    "to_name": "img-1",
                    "type": "keypointlabels",
                    "origin": "manual"
                },
                {
                    "original_width": 640,
                    "original_height": 360,
                    "image_rotation": 0,
                    "value": {
                        "x": 45.83974361419678,
                        "y": 33.82290310329861,
                        "width": 0.22471910112359553,
                        "keypointlabels": [
                            "right_hip"
                        ]
                    },
                    "from_name": "kp-1",
                    "to_name": "img-1",
                    "type": "keypointlabels",
                    "origin": "manual"
                },
                {
                    "original_width": 640,
                    "original_height": 360,
                    "image_rotation": 0,
                    "value": {
                        "x": 47.31881618499756,
                        "y": 40.675743950737846,
                        "width": 0.22471910112359553,
                        "keypointlabels": [
                            "left_knee"
                        ]
                    },
                    "from_name": "kp-1",
                    "to_name": "img-1",
                    "type": "keypointlabels",
                    "origin": "manual"
                },
                {
                    "original_width": 640,
                    "original_height": 360,
                    "image_rotation": 0,
                    "value": {
                        "x": 45.727524757385254,
                        "y": 41.883231268988716,
                        "width": 0.22471910112359553,
                        "keypointlabels": [
                            "right_knee"
                        ]
                    },
                    "from_name": "kp-1",
                    "to_name": "img-1",
                    "type": "keypointlabels",
                    "origin": "manual"
                },
                {
                    "original_width": 640,
                    "original_height": 360,
                    "image_rotation": 0,
                    "value": {
                        "x": 0.0,
                        "y": 0.0,
                        "width": 0.22471910112359553,
                        "keypointlabels": [
                            "left_ankle"
                        ]
                    },
                    "from_name": "kp-1",
                    "to_name": "img-1",
                    "type": "keypointlabels",
                    "origin": "manual"
                },
                {
                    "original_width": 640,
                    "original_height": 360,
                    "image_rotation": 0,
                    "value": {
                        "x": 43.43170642852783,
                        "y": 47.51848432752821,
                        "width": 0.22471910112359553,
                        "keypointlabels": [
                            "right_ankle"
                        ]
                    },
                    "from_name": "kp-1",
                    "to_name": "img-1",
                    "type": "keypointlabels",
                    "origin": "manual"
                },
                {
                    "original_width": 640,
                    "original_height": 360,
                    "image_rotation": 0,
                    "value": {
                        "x": 42.65625,
                        "y": 11.11111111111111,
                        "width": 6.5625,
                        "height": 40.833333333333336,
                        "rectanglelabels": [
                            "People"
                        ]
                    },
                    "from_name": "label",
                    "to_name": "img-1",
                    "type": "rectanglelabels",
                    "origin": "manual"
                },
                {
                    "original_width": 640,
                    "original_height": 360,
                    "image_rotation": 0,
                    "value": {
                        "x": 0.0,
                        "y": 0.0,
                        "width": 0.22471910112359553,
                        "keypointlabels": [
                            "nose"
                        ]
                    },
                    "from_name": "kp-1",
                    "to_name": "img-1",
                    "type": "keypointlabels",
                    "origin": "manual"
                },
                {
                    "original_width": 640,
                    "original_height": 360,
                    "image_rotation": 0,
                    "value": {
                        "x": 21.85446262359619,
                        "y": 13.027795155843098,
                        "width": 0.22471910112359553,
                        "keypointlabels": [
                            "left_shoulder"
                        ]
                    },
                    "from_name": "kp-1",
                    "to_name": "img-1",
                    "type": "keypointlabels",
                    "origin": "manual"
                },
                {
                    "original_width": 640,
                    "original_height": 360,
                    "image_rotation": 0,
                    "value": {
                        "x": 23.973617553710938,
                        "y": 10.542560153537327,
                        "width": 0.22471910112359553,
                        "keypointlabels": [
                            "right_shoulder"
                        ]
                    },
                    "from_name": "kp-1",
                    "to_name": "img-1",
                    "type": "keypointlabels",
                    "origin": "manual"
                },
                {
                    "original_width": 640,
                    "original_height": 360,
                    "image_rotation": 0,
                    "value": {
                        "x": 23.844616413116455,
                        "y": 19.48116938273112,
                        "width": 0.22471910112359553,
                        "keypointlabels": [
                            "left_elbow"
                        ]
                    },
                    "from_name": "kp-1",
                    "to_name": "img-1",
                    "type": "keypointlabels",
                    "origin": "manual"
                },
                {
                    "original_width": 640,
                    "original_height": 360,
                    "image_rotation": 0,
                    "value": {
                        "x": 0.0,
                        "y": 0.0,
                        "width": 0.22471910112359553,
                        "keypointlabels": [
                            "right_elbow"
                        ]
                    },
                    "from_name": "kp-1",
                    "to_name": "img-1",
                    "type": "keypointlabels",
                    "origin": "manual"
                },
                {
                    "original_width": 640,
                    "original_height": 360,
                    "image_rotation": 0,
                    "value": {
                        "x": 22.35574960708618,
                        "y": 21.72538333468967,
                        "width": 0.22471910112359553,
                        "keypointlabels": [
                            "left_wrist"
                        ]
                    },
                    "from_name": "kp-1",
                    "to_name": "img-1",
                    "type": "keypointlabels",
                    "origin": "manual"
                },
                {
                    "original_width": 640,
                    "original_height": 360,
                    "image_rotation": 0,
                    "value": {
                        "x": 0.0,
                        "y": 0.0,
                        "width": 0.22471910112359553,
                        "keypointlabels": [
                            "right_wrist"
                        ]
                    },
                    "from_name": "kp-1",
                    "to_name": "img-1",
                    "type": "keypointlabels",
                    "origin": "manual"
                },
                {
                    "original_width": 640,
                    "original_height": 360,
                    "image_rotation": 0,
                    "value": {
                        "x": 24.937093257904053,
                        "y": 24.122744666205513,
                        "width": 0.22471910112359553,
                        "keypointlabels": [
                            "left_hip"
                        ]
                    },
                    "from_name": "kp-1",
                    "to_name": "img-1",
                    "type": "keypointlabels",
                    "origin": "manual"
                },
                {
                    "original_width": 640,
                    "original_height": 360,
                    "image_rotation": 0,
                    "value": {
                        "x": 26.56683921813965,
                        "y": 23.019303215874565,
                        "width": 0.22471910112359553,
                        "keypointlabels": [
                            "right_hip"
                        ]
                    },
                    "from_name": "kp-1",
                    "to_name": "img-1",
                    "type": "keypointlabels",
                    "origin": "manual"
                },
                {
                    "original_width": 640,
                    "original_height": 360,
                    "image_rotation": 0,
                    "value": {
                        "x": 26.037256717681885,
                        "y": 31.841447618272568,
                        "width": 0.22471910112359553,
                        "keypointlabels": [
                            "left_knee"
                        ]
                    },
                    "from_name": "kp-1",
                    "to_name": "img-1",
                    "type": "keypointlabels",
                    "origin": "manual"
                },
                {
                    "original_width": 640,
                    "original_height": 360,
                    "image_rotation": 0,
                    "value": {
                        "x": 28.25080633163452,
                        "y": 30.443920559353298,
                        "width": 0.22471910112359553,
                        "keypointlabels": [
                            "right_knee"
                        ]
                    },
                    "from_name": "kp-1",
                    "to_name": "img-1",
                    "type": "keypointlabels",
                    "origin": "manual"
                },
                {
                    "original_width": 640,
                    "original_height": 360,
                    "image_rotation": 0,
                    "value": {
                        "x": 27.26154088973999,
                        "y": 38.48432752821181,
                        "width": 0.22471910112359553,
                        "keypointlabels": [
                            "left_ankle"
                        ]
                    },
                    "from_name": "kp-1",
                    "to_name": "img-1",
                    "type": "keypointlabels",
                    "origin": "manual"
                },
                {
                    "original_width": 640,
                    "original_height": 360,
                    "image_rotation": 0,
                    "value": {
                        "x": 29.699203968048096,
                        "y": 36.9134267171224,
                        "width": 0.22471910112359553,
                        "keypointlabels": [
                            "right_ankle"
                        ]
                    },
                    "from_name": "kp-1",
                    "to_name": "img-1",
                    "type": "keypointlabels",
                    "origin": "manual"
                },
                {
                    "original_width": 640,
                    "original_height": 360,
                    "image_rotation": 0,
                    "value": {
                        "x": 19.375,
                        "y": 1.9444444444444444,
                        "width": 11.09375,
                        "height": 38.05555555555556,
                        "rectanglelabels": [
                            "People"
                        ]
                    },
                    "from_name": "label",
                    "to_name": "img-1",
                    "type": "rectanglelabels",
                    "origin": "manual"
                },
                {
                    "original_width": 640,
                    "original_height": 360,
                    "image_rotation": 0,
                    "value": {
                        "x": 0.0,
                        "y": 0.0,
                        "width": 0.22471910112359553,
                        "keypointlabels": [
                            "nose"
                        ]
                    },
                    "from_name": "kp-1",
                    "to_name": "img-1",
                    "type": "keypointlabels",
                    "origin": "manual"
                },
                {
                    "original_width": 640,
                    "original_height": 360,
                    "image_rotation": 0,
                    "value": {
                        "x": 70.86780071258545,
                        "y": 57.416788736979164,
                        "width": 0.22471910112359553,
                        "keypointlabels": [
                            "left_shoulder"
                        ]
                    },
                    "from_name": "kp-1",
                    "to_name": "img-1",
                    "type": "keypointlabels",
                    "origin": "manual"
                },
                {
                    "original_width": 640,
                    "original_height": 360,
                    "image_rotation": 0,
                    "value": {
                        "x": 75.99907875061035,
                        "y": 43.924407958984375,
                        "width": 0.22471910112359553,
                        "keypointlabels": [
                            "right_shoulder"
                        ]
                    },
                    "from_name": "kp-1",
                    "to_name": "img-1",
                    "type": "keypointlabels",
                    "origin": "manual"
                },
                {
                    "original_width": 640,
                    "original_height": 360,
                    "image_rotation": 0,
                    "value": {
                        "x": 67.9863977432251,
                        "y": 72.83952501085069,
                        "width": 0.22471910112359553,
                        "keypointlabels": [
                            "left_elbow"
                        ]
                    },
                    "from_name": "kp-1",
                    "to_name": "img-1",
                    "type": "keypointlabels",
                    "origin": "manual"
                },
                {
                    "original_width": 640,
                    "original_height": 360,
                    "image_rotation": 0,
                    "value": {
                        "x": 0.0,
                        "y": 0.0,
                        "width": 0.22471910112359553,
                        "keypointlabels": [
                            "right_elbow"
                        ]
                    },
                    "from_name": "kp-1",
                    "to_name": "img-1",
                    "type": "keypointlabels",
                    "origin": "manual"
                },
                {
                    "original_width": 640,
                    "original_height": 360,
                    "image_rotation": 0,
                    "value": {
                        "x": 0.0,
                        "y": 0.0,
                        "width": 0.22471910112359553,
                        "keypointlabels": [
                            "left_wrist"
                        ]
                    },
                    "from_name": "kp-1",
                    "to_name": "img-1",
                    "type": "keypointlabels",
                    "origin": "manual"
                },
                {
                    "original_width": 640,
                    "original_height": 360,
                    "image_rotation": 0,
                    "value": {
                        "x": 0.0,
                        "y": 0.0,
                        "width": 0.22471910112359553,
                        "keypointlabels": [
                            "right_wrist"
                        ]
                    },
                    "from_name": "kp-1",
                    "to_name": "img-1",
                    "type": "keypointlabels",
                    "origin": "manual"
                },
                {
                    "original_width": 640,
                    "original_height": 360,
                    "image_rotation": 0,
                    "value": {
                        "x": 70.68600177764893,
                        "y": 76.02825588650174,
                        "width": 0.22471910112359553,
                        "keypointlabels": [
                            "left_hip"
                        ]
                    },
                    "from_name": "kp-1",
                    "to_name": "img-1",
                    "type": "keypointlabels",
                    "origin": "manual"
                },
                {
                    "original_width": 640,
                    "original_height": 360,
                    "image_rotation": 0,
                    "value": {
                        "x": 74.1018295288086,
                        "y": 69.45616828070746,
                        "width": 0.22471910112359553,
                        "keypointlabels": [
                            "right_hip"
                        ]
                    },
                    "from_name": "kp-1",
                    "to_name": "img-1",
                    "type": "keypointlabels",
                    "origin": "manual"
                },
                {
                    "original_width": 640,
                    "original_height": 360,
                    "image_rotation": 0,
                    "value": {
                        "x": 0.0,
                        "y": 0.0,
                        "width": 0.22471910112359553,
                        "keypointlabels": [
                            "left_knee"
                        ]
                    },
                    "from_name": "kp-1",
                    "to_name": "img-1",
                    "type": "keypointlabels",
                    "origin": "manual"
                },
                {
                    "original_width": 640,
                    "original_height": 360,
                    "image_rotation": 0,
                    "value": {
                        "x": 0.0,
                        "y": 0.0,
                        "width": 0.22471910112359553,
                        "keypointlabels": [
                            "right_knee"
                        ]
                    },
                    "from_name": "kp-1",
                    "to_name": "img-1",
                    "type": "keypointlabels",
                    "origin": "manual"
                },
                {
                    "original_width": 640,
                    "original_height": 360,
                    "image_rotation": 0,
                    "value": {
                        "x": 0.0,
                        "y": 0.0,
                        "width": 0.22471910112359553,
                        "keypointlabels": [
                            "left_ankle"
                        ]
                    },
                    "from_name": "kp-1",
                    "to_name": "img-1",
                    "type": "keypointlabels",
                    "origin": "manual"
                },
                {
                    "original_width": 640,
                    "original_height": 360,
                    "image_rotation": 0,
                    "value": {
                        "x": 0.0,
                        "y": 0.0,
                        "width": 0.22471910112359553,
                        "keypointlabels": [
                            "right_ankle"
                        ]
                    },
                    "from_name": "kp-1",
                    "to_name": "img-1",
                    "type": "keypointlabels",
                    "origin": "manual"
                },
                {
                    "original_width": 640,
                    "original_height": 360,
                    "image_rotation": 0,
                    "value": {
                        "x": 62.5,
                        "y": 33.61111111111111,
                        "width": 17.1875,
                        "height": 46.388888888888886,
                        "rectanglelabels": [
                            "People"
                        ]
                    },
                    "from_name": "label",
                    "to_name": "img-1",
                    "type": "rectanglelabels",
                    "origin": "manual"
                },
                {
                    "original_width": 640,
                    "original_height": 360,
                    "image_rotation": 0,
                    "value": {
                        "x": 0.0,
                        "y": 0.0,
                        "width": 0.22471910112359553,
                        "keypointlabels": [
                            "nose"
                        ]
                    },
                    "from_name": "kp-1",
                    "to_name": "img-1",
                    "type": "keypointlabels",
                    "origin": "manual"
                },
                {
                    "original_width": 640,
                    "original_height": 360,
                    "image_rotation": 0,
                    "value": {
                        "x": 22.42894172668457,
                        "y": 17.047678629557293,
                        "width": 0.22471910112359553,
                        "keypointlabels": [
                            "left_shoulder"
                        ]
                    },
                    "from_name": "kp-1",
                    "to_name": "img-1",
                    "type": "keypointlabels",
                    "origin": "manual"
                },
                {
                    "original_width": 640,
                    "original_height": 360,
                    "image_rotation": 0,
                    "value": {
                        "x": 0.0,
                        "y": 0.0,
                        "width": 0.22471910112359553,
                        "keypointlabels": [
                            "right_shoulder"
                        ]
                    },
                    "from_name": "kp-1",
                    "to_name": "img-1",
                    "type": "keypointlabels",
                    "origin": "manual"
                },
                {
                    "original_width": 640,
                    "original_height": 360,
                    "image_rotation": 0,
                    "value": {
                        "x": 23.372483253479004,
                        "y": 19.968736436631943,
                        "width": 0.22471910112359553,
                        "keypointlabels": [
                            "left_elbow"
                        ]
                    },
                    "from_name": "kp-1",
                    "to_name": "img-1",
                    "type": "keypointlabels",
                    "origin": "manual"
                },
                {
                    "original_width": 640,
                    "original_height": 360,
                    "image_rotation": 0,
                    "value": {
                        "x": 0.0,
                        "y": 0.0,
                        "width": 0.22471910112359553,
                        "keypointlabels": [
                            "right_elbow"
                        ]
                    },
                    "from_name": "kp-1",
                    "to_name": "img-1",
                    "type": "keypointlabels",
                    "origin": "manual"
                },
                {
                    "original_width": 640,
                    "original_height": 360,
                    "image_rotation": 0,
                    "value": {
                        "x": 22.03794002532959,
                        "y": 21.764712863498264,
                        "width": 0.22471910112359553,
                        "keypointlabels": [
                            "left_wrist"
                        ]
                    },
                    "from_name": "kp-1",
                    "to_name": "img-1",
                    "type": "keypointlabels",
                    "origin": "manual"
                },
                {
                    "original_width": 640,
                    "original_height": 360,
                    "image_rotation": 0,
                    "value": {
                        "x": 0.0,
                        "y": 0.0,
                        "width": 0.22471910112359553,
                        "keypointlabels": [
                            "right_wrist"
                        ]
                    },
                    "from_name": "kp-1",
                    "to_name": "img-1",
                    "type": "keypointlabels",
                    "origin": "manual"
                },
                {
                    "original_width": 640,
                    "original_height": 360,
                    "image_rotation": 0,
                    "value": {
                        "x": 24.94136095046997,
                        "y": 24.31095971001519,
                        "width": 0.22471910112359553,
                        "keypointlabels": [
                            "left_hip"
                        ]
                    },
                    "from_name": "kp-1",
                    "to_name": "img-1",
                    "type": "keypointlabels",
                    "origin": "manual"
                },
                {
                    "original_width": 640,
                    "original_height": 360,
                    "image_rotation": 0,
                    "value": {
                        "x": 26.39981985092163,
                        "y": 23.880939483642578,
                        "width": 0.22471910112359553,
                        "keypointlabels": [
                            "right_hip"
                        ]
                    },
                    "from_name": "kp-1",
                    "to_name": "img-1",
                    "type": "keypointlabels",
                    "origin": "manual"
                },
                {
                    "original_width": 640,
                    "original_height": 360,
                    "image_rotation": 0,
                    "value": {
                        "x": 26.030983924865723,
                        "y": 31.605370839436848,
                        "width": 0.22471910112359553,
                        "keypointlabels": [
                            "left_knee"
                        ]
                    },
                    "from_name": "kp-1",
                    "to_name": "img-1",
                    "type": "keypointlabels",
                    "origin": "manual"
                },
                {
                    "original_width": 640,
                    "original_height": 360,
                    "image_rotation": 0,
                    "value": {
                        "x": 27.95722723007202,
                        "y": 30.52867677476671,
                        "width": 0.22471910112359553,
                        "keypointlabels": [
                            "right_knee"
                        ]
                    },
                    "from_name": "kp-1",
                    "to_name": "img-1",
                    "type": "keypointlabels",
                    "origin": "manual"
                },
                {
                    "original_width": 640,
                    "original_height": 360,
                    "image_rotation": 0,
                    "value": {
                        "x": 27.20228672027588,
                        "y": 38.54473114013672,
                        "width": 0.22471910112359553,
                        "keypointlabels": [
                            "left_ankle"
                        ]
                    },
                    "from_name": "kp-1",
                    "to_name": "img-1",
                    "type": "keypointlabels",
                    "origin": "manual"
                },
                {
                    "original_width": 640,
                    "original_height": 360,
                    "image_rotation": 0,
                    "value": {
                        "x": 29.474711418151855,
                        "y": 36.70559353298611,
                        "width": 0.22471910112359553,
                        "keypointlabels": [
                            "right_ankle"
                        ]
                    },
                    "from_name": "kp-1",
                    "to_name": "img-1",
                    "type": "keypointlabels",
                    "origin": "manual"
                },
                {
                    "original_width": 640,
                    "original_height": 360,
                    "image_rotation": 0,
                    "value": {
                        "x": 20.15625,
                        "y": 18.333333333333332,
                        "width": 10.3125,
                        "height": 21.38888888888889,
                        "rectanglelabels": [
                            "People"
                        ]
                    },
                    "from_name": "label",
                    "to_name": "img-1",
                    "type": "rectanglelabels",
                    "origin": "manual"
                }
            ]
        }
    ]
}
