{
    "data": {
        "img": "/data/local-files?d=industry_safety_0/rgb_02759_3.jpg"
    },
    "predictions": [
        {
            "result": [
                {
                    "original_width": 640,
                    "original_height": 360,
                    "image_rotation": 0,
                    "value": {
                        "x": 77.12603569030762,
                        "y": 26.09966278076172,
                        "width": 0.22471910112359553,
                        "keypointlabels": [
                            "nose"
                        ]
                    },
                    "from_name": "kp-1",
                    "to_name": "img-1",
                    "type": "keypointlabels",
                    "origin": "manual"
                },
                {
                    "original_width": 640,
                    "original_height": 360,
                    "image_rotation": 0,
                    "value": {
                        "x": 78.88751983642578,
                        "y": 35.41778988308376,
                        "width": 0.22471910112359553,
                        "keypointlabels": [
                            "left_shoulder"
                        ]
                    },
                    "from_name": "kp-1",
                    "to_name": "img-1",
                    "type": "keypointlabels",
                    "origin": "manual"
                },
                {
                    "original_width": 640,
                    "original_height": 360,
                    "image_rotation": 0,
                    "value": {
                        "x": 83.08907508850098,
                        "y": 32.747391594780815,
                        "width": 0.22471910112359553,
                        "keypointlabels": [
                            "right_shoulder"
                        ]
                    },
                    "from_name": "kp-1",
                    "to_name": "img-1",
                    "type": "keypointlabels",
                    "origin": "manual"
                },
                {
                    "original_width": 640,
                    "original_height": 360,
                    "image_rotation": 0,
                    "value": {
                        "x": 75.24796962738037,
                        "y": 45.94515482584635,
                        "width": 0.22471910112359553,
                        "keypointlabels": [
                            "left_elbow"
                        ]
                    },
                    "from_name": "kp-1",
                    "to_name": "img-1",
                    "type": "keypointlabels",
                    "origin": "manual"
                },
                {
                    "original_width": 640,
                    "original_height": 360,
                    "image_rotation": 0,
                    "value": {
                        "x": 78.4372615814209,
                        "y": 38.24891832139757,
                        "width": 0.22471910112359553,
                        "keypointlabels": [
                            "right_elbow"
                        ]
                    },
                    "from_name": "kp-1",
                    "to_name": "img-1",
                    "type": "keypointlabels",
                    "origin": "manual"
                },
                {
                    "original_width": 640,
                    "original_height": 360,
                    "image_rotation": 0,
                    "value": {
                        "x": 72.65389442443848,
                        "y": 39.415783352322045,
                        "width": 0.22471910112359553,
                        "keypointlabels": [
                            "left_wrist"
                        ]
                    },
                    "from_name": "kp-1",
                    "to_name": "img-1",
                    "type": "keypointlabels",
                    "origin": "manual"
                },
                {
                    "original_width": 640,
                    "original_height": 360,
                    "image_rotation": 0,
                    "value": {
                        "x": 74.39297676086426,
                        "y": 36.175621880425346,
                        "width": 0.22471910112359553,
                        "keypointlabels": [
                            "right_wrist"
                        ]
                    },
                    "from_name": "kp-1",
                    "to_name": "img-1",
                    "type": "keypointlabels",
                    "origin": "manual"
                },
                {
                    "original_width": 640,
                    "original_height": 360,
                    "image_rotation": 0,
                    "value": {
                        "x": 74.05914306640625,
                        "y": 53.06891123453776,
                        "width": 0.22471910112359553,
                        "keypointlabels": [
                            "left_hip"
                        ]
                    },
                    "from_name": "kp-1",
                    "to_name": "img-1",
                    "type": "keypointlabels",
                    "origin": "manual"
                },
                {
                    "original_width": 640,
                    "original_height": 360,
                    "image_rotation": 0,
                    "value": {
                        "x": 77.46492862701416,
                        "y": 51.40208774142795,
                        "width": 0.22471910112359553,
                        "keypointlabels": [
                            "right_hip"
                        ]
                    },
                    "from_name": "kp-1",
                    "to_name": "img-1",
                    "type": "keypointlabels",
                    "origin": "manual"
                },
                {
                    "original_width": 640,
                    "original_height": 360,
                    "image_rotation": 0,
                    "value": {
                        "x": 69.27586555480957,
                        "y": 59.60165659586588,
                        "width": 0.22471910112359553,
                        "keypointlabels": [
                            "left_knee"
                        ]
                    },
                    "from_name": "kp-1",
                    "to_name": "img-1",
                    "type": "keypointlabels",
                    "origin": "manual"
                },
                {
                    "original_width": 640,
                    "original_height": 360,
                    "image_rotation": 0,
                    "value": {
                        "x": 73.6341381072998,
                        "y": 60.04238976372613,
                        "width": 0.22471910112359553,
                        "keypointlabels": [
                            "right_knee"
                        ]
                    },
                    "from_name": "kp-1",
                    "to_name": "img-1",
                    "type": "keypointlabels",
                    "origin": "manual"
                },
                {
                    "original_width": 640,
                    "original_height": 360,
                    "image_rotation": 0,
                    "value": {
                        "x": 67.04940795898438,
                        "y": 67.07161373562283,
                        "width": 0.22471910112359553,
                        "keypointlabels": [
                            "left_ankle"
                        ]
                    },
                    "from_name": "kp-1",
                    "to_name": "img-1",
                    "type": "keypointlabels",
                    "origin": "manual"
                },
                {
                    "original_width": 640,
                    "original_height": 360,
                    "image_rotation": 0,
                    "value": {
                        "x": 72.4043607711792,
                        "y": 67.37183464898003,
                        "width": 0.22471910112359553,
                        "keypointlabels": [
                            "right_ankle"
                        ]
                    },
                    "from_name": "kp-1",
                    "to_name": "img-1",
                    "type": "keypointlabels",
                    "origin": "manual"
                },
                {
                    "original_width": 640,
                    "original_height": 360,
                    "image_rotation": 0,
                    "value": {
                        "x": 62.8125,
                        "y": 18.055555555555554,
                        "width": 21.40625,
                        "height": 51.666666666666664,
                        "rectanglelabels": [
                            "People"
                        ]
                    },
                    "from_name": "label",
                    "to_name": "img-1",
                    "type": "rectanglelabels",
                    "origin": "manual"
                },
                {
                    "original_width": 640,
                    "original_height": 360,
                    "image_rotation": 0,
                    "value": {
                        "x": 59.11263942718506,
                        "y": 50.357674492730034,
                        "width": 0.22471910112359553,
                        "keypointlabels": [
                            "nose"
                        ]
                    },
                    "from_name": "kp-1",
                    "to_name": "img-1",
                    "type": "keypointlabels",
                    "origin": "manual"
                },
                {
                    "original_width": 640,
                    "original_height": 360,
                    "image_rotation": 0,
                    "value": {
                        "x": 57.12183475494385,
                        "y": 51.71685112847222,
                        "width": 0.22471910112359553,
                        "keypointlabels": [
                            "left_shoulder"
                        ]
                    },
                    "from_name": "kp-1",
                    "to_name": "img-1",
                    "type": "keypointlabels",
                    "origin": "manual"
                },
                {
                    "original_width": 640,
                    "original_height": 360,
                    "image_rotation": 0,
                    "value": {
                        "x": 52.73284435272217,
                        "y": 57.54817114935981,
                        "width": 0.22471910112359553,
                        "keypointlabels": [
                            "right_shoulder"
                        ]
                    },
                    "from_name": "kp-1",
                    "to_name": "img-1",
                    "type": "keypointlabels",
                    "origin": "manual"
                },
                {
                    "original_width": 640,
                    "original_height": 360,
                    "image_rotation": 0,
                    "value": {
                        "x": 58.96608352661133,
                        "y": 60.418701171875,
                        "width": 0.22471910112359553,
                        "keypointlabels": [
                            "left_elbow"
                        ]
                    },
                    "from_name": "kp-1",
                    "to_name": "img-1",
                    "type": "keypointlabels",
                    "origin": "manual"
                },
                {
                    "original_width": 640,
                    "original_height": 360,
                    "image_rotation": 0,
                    "value": {
                        "x": 55.16083240509033,
                        "y": 72.18612670898438,
                        "width": 0.22471910112359553,
                        "keypointlabels": [
                            "right_elbow"
                        ]
                    },
                    "from_name": "kp-1",
                    "to_name": "img-1",
                    "type": "keypointlabels",
                    "origin": "manual"
                },
                {
                    "original_width": 640,
                    "original_height": 360,
                    "image_rotation": 0,
                    "value": {
                        "x": 61.10485553741455,
                        "y": 67.4994871351454,
                        "width": 0.22471910112359553,
                        "keypointlabels": [
                            "left_wrist"
                        ]
                    },
                    "from_name": "kp-1",
                    "to_name": "img-1",
                    "type": "keypointlabels",
                    "origin": "manual"
                },
                {
                    "original_width": 640,
                    "original_height": 360,
                    "image_rotation": 0,
                    "value": {
                        "x": 63.55267524719238,
                        "y": 71.76450093587239,
                        "width": 0.22471910112359553,
                        "keypointlabels": [
                            "right_wrist"
                        ]
                    },
                    "from_name": "kp-1",
                    "to_name": "img-1",
                    "type": "keypointlabels",
                    "origin": "manual"
                },
                {
                    "original_width": 640,
                    "original_height": 360,
                    "image_rotation": 0,
                    "value": {
                        "x": 56.948184967041016,
                        "y": 72.75429619683159,
                        "width": 0.22471910112359553,
                        "keypointlabels": [
                            "left_hip"
                        ]
                    },
                    "from_name": "kp-1",
                    "to_name": "img-1",
                    "type": "keypointlabels",
                    "origin": "manual"
                },
                {
                    "original_width": 640,
                    "original_height": 360,
                    "image_rotation": 0,
                    "value": {
                        "x": 54.10623550415039,
                        "y": 75.73107401529948,
                        "width": 0.22471910112359553,
                        "keypointlabels": [
                            "right_hip"
                        ]
                    },
                    "from_name": "kp-1",
                    "to_name": "img-1",
                    "type": "keypointlabels",
                    "origin": "manual"
                },
                {
                    "original_width": 640,
                    "original_height": 360,
                    "image_rotation": 0,
                    "value": {
                        "x": 55.72329521179199,
                        "y": 83.1016116672092,
                        "width": 0.22471910112359553,
                        "keypointlabels": [
                            "left_knee"
                        ]
                    },
                    "from_name": "kp-1",
                    "to_name": "img-1",
                    "type": "keypointlabels",
                    "origin": "manual"
                },
                {
                    "original_width": 640,
                    "original_height": 360,
                    "image_rotation": 0,
                    "value": {
                        "x": 54.40778732299805,
                        "y": 85.88572184244792,
                        "width": 0.22471910112359553,
                        "keypointlabels": [
                            "right_knee"
                        ]
                    },
                    "from_name": "kp-1",
                    "to_name": "img-1",
                    "type": "keypointlabels",
                    "origin": "manual"
                },
                {
                    "original_width": 640,
                    "original_height": 360,
                    "image_rotation": 0,
                    "value": {
                        "x": 54.25856590270996,
                        "y": 85.4002465142144,
                        "width": 0.22471910112359553,
                        "keypointlabels": [
                            "left_ankle"
                        ]
                    },
                    "from_name": "kp-1",
                    "to_name": "img-1",
                    "type": "keypointlabels",
                    "origin": "manual"
                },
                {
                    "original_width": 640,
                    "original_height": 360,
                    "image_rotation": 0,
                    "value": {
                        "x": 52.877535820007324,
                        "y": 90.65008375379774,
                        "width": 0.22471910112359553,
                        "keypointlabels": [
                            "right_ankle"
                        ]
                    },
                    "from_name": "kp-1",
                    "to_name": "img-1",
                    "type": "keypointlabels",
                    "origin": "manual"
                },
                {
                    "original_width": 640,
                    "original_height": 360,
                    "image_rotation": 0,
                    "value": {
                        "x": 50.0,
                        "y": 35.0,
                        "width": 17.8125,
                        "height": 62.77777777777778,
                        "rectanglelabels": [
                            "People"
                        ]
                    },
                    "from_name": "label",
                    "to_name": "img-1",
                    "type": "rectanglelabels",
                    "origin": "manual"
                },
                {
                    "original_width": 640,
                    "original_height": 360,
                    "image_rotation": 0,
                    "value": {
                        "x": 0.0,
                        "y": 0.0,
                        "width": 0.22471910112359553,
                        "keypointlabels": [
                            "nose"
                        ]
                    },
                    "from_name": "kp-1",
                    "to_name": "img-1",
                    "type": "keypointlabels",
                    "origin": "manual"
                },
                {
                    "original_width": 640,
                    "original_height": 360,
                    "image_rotation": 0,
                    "value": {
                        "x": 20.755834579467773,
                        "y": 15.819827185736761,
                        "width": 0.22471910112359553,
                        "keypointlabels": [
                            "left_shoulder"
                        ]
                    },
                    "from_name": "kp-1",
                    "to_name": "img-1",
                    "type": "keypointlabels",
                    "origin": "manual"
                },
                {
                    "original_width": 640,
                    "original_height": 360,
                    "image_rotation": 0,
                    "value": {
                        "x": 24.739737510681152,
                        "y": 9.751530753241644,
                        "width": 0.22471910112359553,
                        "keypointlabels": [
                            "right_shoulder"
                        ]
                    },
                    "from_name": "kp-1",
                    "to_name": "img-1",
                    "type": "keypointlabels",
                    "origin": "manual"
                },
                {
                    "original_width": 640,
                    "original_height": 360,
                    "image_rotation": 0,
                    "value": {
                        "x": 22.098960876464844,
                        "y": 23.796005249023438,
                        "width": 0.22471910112359553,
                        "keypointlabels": [
                            "left_elbow"
                        ]
                    },
                    "from_name": "kp-1",
                    "to_name": "img-1",
                    "type": "keypointlabels",
                    "origin": "manual"
                },
                {
                    "original_width": 640,
                    "original_height": 360,
                    "image_rotation": 0,
                    "value": {
                        "x": 26.444993019104004,
                        "y": 6.063994301689996,
                        "width": 0.22471910112359553,
                        "keypointlabels": [
                            "right_elbow"
                        ]
                    },
                    "from_name": "kp-1",
                    "to_name": "img-1",
                    "type": "keypointlabels",
                    "origin": "manual"
                },
                {
                    "original_width": 640,
                    "original_height": 360,
                    "image_rotation": 0,
                    "value": {
                        "x": 0.0,
                        "y": 0.0,
                        "width": 0.22471910112359553,
                        "keypointlabels": [
                            "left_wrist"
                        ]
                    },
                    "from_name": "kp-1",
                    "to_name": "img-1",
                    "type": "keypointlabels",
                    "origin": "manual"
                },
                {
                    "original_width": 640,
                    "original_height": 360,
                    "image_rotation": 0,
                    "value": {
                        "x": 25.094945430755615,
                        "y": 1.867629157172309,
                        "width": 0.22471910112359553,
                        "keypointlabels": [
                            "right_wrist"
                        ]
                    },
                    "from_name": "kp-1",
                    "to_name": "img-1",
                    "type": "keypointlabels",
                    "origin": "manual"
                },
                {
                    "original_width": 640,
                    "original_height": 360,
                    "image_rotation": 0,
                    "value": {
                        "x": 24.98668909072876,
                        "y": 27.04527113172743,
                        "width": 0.22471910112359553,
                        "keypointlabels": [
                            "left_hip"
                        ]
                    },
                    "from_name": "kp-1",
                    "to_name": "img-1",
                    "type": "keypointlabels",
                    "origin": "manual"
                },
                {
                    "original_width": 640,
                    "original_height": 360,
                    "image_rotation": 0,
                    "value": {
                        "x": 27.688724994659424,
                        "y": 24.801114400227863,
                        "width": 0.22471910112359553,
                        "keypointlabels": [
                            "right_hip"
                        ]
                    },
                    "from_name": "kp-1",
                    "to_name": "img-1",
                    "type": "keypointlabels",
                    "origin": "manual"
                },
                {
                    "original_width": 640,
                    "original_height": 360,
                    "image_rotation": 0,
                    "value": {
                        "x": 27.195990085601807,
                        "y": 34.500486585828995,
                        "width": 0.22471910112359553,
                        "keypointlabels": [
                            "left_knee"
                        ]
                    },
                    "from_name": "kp-1",
                    "to_name": "img-1",
                    "type": "keypointlabels",
                    "origin": "manual"
                },
                {
                    "original_width": 640,
                    "original_height": 360,
                    "image_rotation": 0,
                    "value": {
                        "x": 29.722278118133545,
                        "y": 33.42379675971137,
                        "width": 0.22471910112359553,
                        "keypointlabels": [
                            "right_knee"
                        ]
                    },
                    "from_name": "kp-1",
                    "to_name": "img-1",
                    "type": "keypointlabels",
                    "origin": "manual"
                },
                {
                    "original_width": 640,
                    "original_height": 360,
                    "image_rotation": 0,
                    "value": {
                        "x": 0.0,
                        "y": 0.0,
                        "width": 0.22471910112359553,
                        "keypointlabels": [
                            "left_ankle"
                        ]
                    },
                    "from_name": "kp-1",
                    "to_name": "img-1",
                    "type": "keypointlabels",
                    "origin": "manual"
                },
                {
                    "original_width": 640,
                    "original_height": 360,
                    "image_rotation": 0,
                    "value": {
                        "x": 31.768076419830322,
                        "y": 39.30193159315321,
                        "width": 0.22471910112359553,
                        "keypointlabels": [
                            "right_ankle"
                        ]
                    },
                    "from_name": "kp-1",
                    "to_name": "img-1",
                    "type": "keypointlabels",
                    "origin": "manual"
                },
                {
                    "original_width": 640,
                    "original_height": 360,
                    "image_rotation": 0,
                    "value": {
                        "x": 19.6875,
                        "y": 0.2777777777777778,
                        "width": 13.4375,
                        "height": 39.44444444444444,
                        "rectanglelabels": [
                            "People"
                        ]
                    },
                    "from_name": "label",
                    "to_name": "img-1",
                    "type": "rectanglelabels",
                    "origin": "manual"
                },
                {
                    "original_width": 640,
                    "original_height": 360,
                    "image_rotation": 0,
                    "value": {
                        "x": 49.18004035949707,
                        "y": 1.2250068452623155,
                        "width": 0.22471910112359553,
                        "keypointlabels": [
                            "nose"
                        ]
                    },
                    "from_name": "kp-1",
                    "to_name": "img-1",
                    "type": "keypointlabels",
                    "origin": "manual"
                },
                {
                    "original_width": 640,
                    "original_height": 360,
                    "image_rotation": 0,
                    "value": {
                        "x": 47.09450721740723,
                        "y": 5.59465832180447,
                        "width": 0.22471910112359553,
                        "keypointlabels": [
                            "left_shoulder"
                        ]
                    },
                    "from_name": "kp-1",
                    "to_name": "img-1",
                    "type": "keypointlabels",
                    "origin": "manual"
                },
                {
                    "original_width": 640,
                    "original_height": 360,
                    "image_rotation": 0,
                    "value": {
                        "x": 45.50299644470215,
                        "y": 6.9101481967502165,
                        "width": 0.22471910112359553,
                        "keypointlabels": [
                            "right_shoulder"
                        ]
                    },
                    "from_name": "kp-1",
                    "to_name": "img-1",
                    "type": "keypointlabels",
                    "origin": "manual"
                },
                {
                    "original_width": 640,
                    "original_height": 360,
                    "image_rotation": 0,
                    "value": {
                        "x": 48.00534725189209,
                        "y": 12.90127224392361,
                        "width": 0.22471910112359553,
                        "keypointlabels": [
                            "left_elbow"
                        ]
                    },
                    "from_name": "kp-1",
                    "to_name": "img-1",
                    "type": "keypointlabels",
                    "origin": "manual"
                },
                {
                    "original_width": 640,
                    "original_height": 360,
                    "image_rotation": 0,
                    "value": {
                        "x": 44.12771701812744,
                        "y": 15.101498497856987,
                        "width": 0.22471910112359553,
                        "keypointlabels": [
                            "right_elbow"
                        ]
                    },
                    "from_name": "kp-1",
                    "to_name": "img-1",
                    "type": "keypointlabels",
                    "origin": "manual"
                },
                {
                    "original_width": 640,
                    "original_height": 360,
                    "image_rotation": 0,
                    "value": {
                        "x": 49.40080165863037,
                        "y": 18.488536410861546,
                        "width": 0.22471910112359553,
                        "keypointlabels": [
                            "left_wrist"
                        ]
                    },
                    "from_name": "kp-1",
                    "to_name": "img-1",
                    "type": "keypointlabels",
                    "origin": "manual"
                },
                {
                    "original_width": 640,
                    "original_height": 360,
                    "image_rotation": 0,
                    "value": {
                        "x": 43.626370429992676,
                        "y": 22.780155605740017,
                        "width": 0.22471910112359553,
                        "keypointlabels": [
                            "right_wrist"
                        ]
                    },
                    "from_name": "kp-1",
                    "to_name": "img-1",
                    "type": "keypointlabels",
                    "origin": "manual"
                },
                {
                    "original_width": 640,
                    "original_height": 360,
                    "image_rotation": 0,
                    "value": {
                        "x": 46.82950496673584,
                        "y": 20.16394721137153,
                        "width": 0.22471910112359553,
                        "keypointlabels": [
                            "left_hip"
                        ]
                    },
                    "from_name": "kp-1",
                    "to_name": "img-1",
                    "type": "keypointlabels",
                    "origin": "manual"
                },
                {
                    "original_width": 640,
                    "original_height": 360,
                    "image_rotation": 0,
                    "value": {
                        "x": 46.08786582946777,
                        "y": 21.096420288085938,
                        "width": 0.22471910112359553,
                        "keypointlabels": [
                            "right_hip"
                        ]
                    },
                    "from_name": "kp-1",
                    "to_name": "img-1",
                    "type": "keypointlabels",
                    "origin": "manual"
                },
                {
                    "original_width": 640,
                    "original_height": 360,
                    "image_rotation": 0,
                    "value": {
                        "x": 46.812682151794434,
                        "y": 28.568945990668404,
                        "width": 0.22471910112359553,
                        "keypointlabels": [
                            "left_knee"
                        ]
                    },
                    "from_name": "kp-1",
                    "to_name": "img-1",
                    "type": "keypointlabels",
                    "origin": "manual"
                },
                {
                    "original_width": 640,
                    "original_height": 360,
                    "image_rotation": 0,
                    "value": {
                        "x": 47.551612854003906,
                        "y": 29.686749776204426,
                        "width": 0.22471910112359553,
                        "keypointlabels": [
                            "right_knee"
                        ]
                    },
                    "from_name": "kp-1",
                    "to_name": "img-1",
                    "type": "keypointlabels",
                    "origin": "manual"
                },
                {
                    "original_width": 640,
                    "original_height": 360,
                    "image_rotation": 0,
                    "value": {
                        "x": 45.76467514038086,
                        "y": 35.18241882324219,
                        "width": 0.22471910112359553,
                        "keypointlabels": [
                            "left_ankle"
                        ]
                    },
                    "from_name": "kp-1",
                    "to_name": "img-1",
                    "type": "keypointlabels",
                    "origin": "manual"
                },
                {
                    "original_width": 640,
                    "original_height": 360,
                    "image_rotation": 0,
                    "value": {
                        "x": 47.27522373199463,
                        "y": 38.11303032769097,
                        "width": 0.22471910112359553,
                        "keypointlabels": [
                            "right_ankle"
                        ]
                    },
                    "from_name": "kp-1",
                    "to_name": "img-1",
                    "type": "keypointlabels",
                    "origin": "manual"
                },
                {
                    "original_width": 640,
                    "original_height": 360,
                    "image_rotation": 0,
                    "value": {
                        "x": 42.8125,
                        "y": 0.0,
                        "width": 8.125,
                        "height": 41.666666666666664,
                        "rectanglelabels": [
                            "People"
                        ]
                    },
                    "from_name": "label",
                    "to_name": "img-1",
                    "type": "rectanglelabels",
                    "origin": "manual"
                },
                {
                    "original_width": 640,
                    "original_height": 360,
                    "image_rotation": 0,
                    "value": {
                        "x": 0.0,
                        "y": 0.0,
                        "width": 0.22471910112359553,
                        "keypointlabels": [
                            "nose"
                        ]
                    },
                    "from_name": "kp-1",
                    "to_name": "img-1",
                    "type": "keypointlabels",
                    "origin": "manual"
                },
                {
                    "original_width": 640,
                    "original_height": 360,
                    "image_rotation": 0,
                    "value": {
                        "x": 52.47373580932617,
                        "y": 18.785599602593315,
                        "width": 0.22471910112359553,
                        "keypointlabels": [
                            "left_shoulder"
                        ]
                    },
                    "from_name": "kp-1",
                    "to_name": "img-1",
                    "type": "keypointlabels",
                    "origin": "manual"
                },
                {
                    "original_width": 640,
                    "original_height": 360,
                    "image_rotation": 0,
                    "value": {
                        "x": 55.136117935180664,
                        "y": 22.262278662787544,
                        "width": 0.22471910112359553,
                        "keypointlabels": [
                            "right_shoulder"
                        ]
                    },
                    "from_name": "kp-1",
                    "to_name": "img-1",
                    "type": "keypointlabels",
                    "origin": "manual"
                },
                {
                    "original_width": 640,
                    "original_height": 360,
                    "image_rotation": 0,
                    "value": {
                        "x": 53.21587085723877,
                        "y": 23.954715728759766,
                        "width": 0.22471910112359553,
                        "keypointlabels": [
                            "left_elbow"
                        ]
                    },
                    "from_name": "kp-1",
                    "to_name": "img-1",
                    "type": "keypointlabels",
                    "origin": "manual"
                },
                {
                    "original_width": 640,
                    "original_height": 360,
                    "image_rotation": 0,
                    "value": {
                        "x": 55.45778274536133,
                        "y": 31.504264407687717,
                        "width": 0.22471910112359553,
                        "keypointlabels": [
                            "right_elbow"
                        ]
                    },
                    "from_name": "kp-1",
                    "to_name": "img-1",
                    "type": "keypointlabels",
                    "origin": "manual"
                },
                {
                    "original_width": 640,
                    "original_height": 360,
                    "image_rotation": 0,
                    "value": {
                        "x": 0.0,
                        "y": 0.0,
                        "width": 0.22471910112359553,
                        "keypointlabels": [
                            "left_wrist"
                        ]
                    },
                    "from_name": "kp-1",
                    "to_name": "img-1",
                    "type": "keypointlabels",
                    "origin": "manual"
                },
                {
                    "original_width": 640,
                    "original_height": 360,
                    "image_rotation": 0,
                    "value": {
                        "x": 57.04695701599121,
                        "y": 27.94891357421875,
                        "width": 0.22471910112359553,
                        "keypointlabels": [
                            "right_wrist"
                        ]
                    },
                    "from_name": "kp-1",
                    "to_name": "img-1",
                    "type": "keypointlabels",
                    "origin": "manual"
                },
                {
                    "original_width": 640,
                    "original_height": 360,
                    "image_rotation": 0,
                    "value": {
                        "x": 52.68069267272949,
                        "y": 34.03358459472656,
                        "width": 0.22471910112359553,
                        "keypointlabels": [
                            "left_hip"
                        ]
                    },
                    "from_name": "kp-1",
                    "to_name": "img-1",
                    "type": "keypointlabels",
                    "origin": "manual"
                },
                {
                    "original_width": 640,
                    "original_height": 360,
                    "image_rotation": 0,
                    "value": {
                        "x": 54.70105171203613,
                        "y": 35.59756384955512,
                        "width": 0.22471910112359553,
                        "keypointlabels": [
                            "right_hip"
                        ]
                    },
                    "from_name": "kp-1",
                    "to_name": "img-1",
                    "type": "keypointlabels",
                    "origin": "manual"
                },
                {
                    "original_width": 640,
                    "original_height": 360,
                    "image_rotation": 0,
                    "value": {
                        "x": 52.96682834625244,
                        "y": 41.875012715657554,
                        "width": 0.22471910112359553,
                        "keypointlabels": [
                            "left_knee"
                        ]
                    },
                    "from_name": "kp-1",
                    "to_name": "img-1",
                    "type": "keypointlabels",
                    "origin": "manual"
                },
                {
                    "original_width": 640,
                    "original_height": 360,
                    "image_rotation": 0,
                    "value": {
                        "x": 54.926748275756836,
                        "y": 43.089561462402344,
                        "width": 0.22471910112359553,
                        "keypointlabels": [
                            "right_knee"
                        ]
                    },
                    "from_name": "kp-1",
                    "to_name": "img-1",
                    "type": "keypointlabels",
                    "origin": "manual"
                },
                {
                    "original_width": 640,
                    "original_height": 360,
                    "image_rotation": 0,
                    "value": {
                        "x": 49.765706062316895,
                        "y": 48.73671637641059,
                        "width": 0.22471910112359553,
                        "keypointlabels": [
                            "left_ankle"
                        ]
                    },
                    "from_name": "kp-1",
                    "to_name": "img-1",
                    "type": "keypointlabels",
                    "origin": "manual"
                },
                {
                    "original_width": 640,
                    "original_height": 360,
                    "image_rotation": 0,
                    "value": {
                        "x": 54.362831115722656,
                        "y": 50.514348347981766,
                        "width": 0.22471910112359553,
                        "keypointlabels": [
                            "right_ankle"
                        ]
                    },
                    "from_name": "kp-1",
                    "to_name": "img-1",
                    "type": "keypointlabels",
                    "origin": "manual"
                },
                {
                    "original_width": 640,
                    "original_height": 360,
                    "image_rotation": 0,
                    "value": {
                        "x": 48.28125,
                        "y": 8.333333333333334,
                        "width": 10.9375,
                        "height": 45.27777777777778,
                        "rectanglelabels": [
                            "People"
                        ]
                    },
                    "from_name": "label",
                    "to_name": "img-1",
                    "type": "rectanglelabels",
                    "origin": "manual"
                },
                {
                    "original_width": 640,
                    "original_height": 360,
                    "image_rotation": 0,
                    "value": {
                        "x": 18.018451929092407,
                        "y": 26.03700213962131,
                        "width": 0.22471910112359553,
                        "keypointlabels": [
                            "nose"
                        ]
                    },
                    "from_name": "kp-1",
                    "to_name": "img-1",
                    "type": "keypointlabels",
                    "origin": "manual"
                },
                {
                    "original_width": 640,
                    "original_height": 360,
                    "image_rotation": 0,
                    "value": {
                        "x": 22.757530212402344,
                        "y": 30.94825956556532,
                        "width": 0.22471910112359553,
                        "keypointlabels": [
                            "left_shoulder"
                        ]
                    },
                    "from_name": "kp-1",
                    "to_name": "img-1",
                    "type": "keypointlabels",
                    "origin": "manual"
                },
                {
                    "original_width": 640,
                    "original_height": 360,
                    "image_rotation": 0,
                    "value": {
                        "x": 22.03605890274048,
                        "y": 26.686297522650825,
                        "width": 0.22471910112359553,
                        "keypointlabels": [
                            "right_shoulder"
                        ]
                    },
                    "from_name": "kp-1",
                    "to_name": "img-1",
                    "type": "keypointlabels",
                    "origin": "manual"
                },
                {
                    "original_width": 640,
                    "original_height": 360,
                    "image_rotation": 0,
                    "value": {
                        "x": 21.404120922088623,
                        "y": 39.30626763237847,
                        "width": 0.22471910112359553,
                        "keypointlabels": [
                            "left_elbow"
                        ]
                    },
                    "from_name": "kp-1",
                    "to_name": "img-1",
                    "type": "keypointlabels",
                    "origin": "manual"
                },
                {
                    "original_width": 640,
                    "original_height": 360,
                    "image_rotation": 0,
                    "value": {
                        "x": 19.105446338653564,
                        "y": 29.56181420220269,
                        "width": 0.22471910112359553,
                        "keypointlabels": [
                            "right_elbow"
                        ]
                    },
                    "from_name": "kp-1",
                    "to_name": "img-1",
                    "type": "keypointlabels",
                    "origin": "manual"
                },
                {
                    "original_width": 640,
                    "original_height": 360,
                    "image_rotation": 0,
                    "value": {
                        "x": 17.04258918762207,
                        "y": 41.840150621202255,
                        "width": 0.22471910112359553,
                        "keypointlabels": [
                            "left_wrist"
                        ]
                    },
                    "from_name": "kp-1",
                    "to_name": "img-1",
                    "type": "keypointlabels",
                    "origin": "manual"
                },
                {
                    "original_width": 640,
                    "original_height": 360,
                    "image_rotation": 0,
                    "value": {
                        "x": 14.291605949401855,
                        "y": 31.807314554850258,
                        "width": 0.22471910112359553,
                        "keypointlabels": [
                            "right_wrist"
                        ]
                    },
                    "from_name": "kp-1",
                    "to_name": "img-1",
                    "type": "keypointlabels",
                    "origin": "manual"
                },
                {
                    "original_width": 640,
                    "original_height": 360,
                    "image_rotation": 0,
                    "value": {
                        "x": 28.194386959075928,
                        "y": 40.99471198187934,
                        "width": 0.22471910112359553,
                        "keypointlabels": [
                            "left_hip"
                        ]
                    },
                    "from_name": "kp-1",
                    "to_name": "img-1",
                    "type": "keypointlabels",
                    "origin": "manual"
                },
                {
                    "original_width": 640,
                    "original_height": 360,
                    "image_rotation": 0,
                    "value": {
                        "x": 27.680726051330566,
                        "y": 39.25386216905382,
                        "width": 0.22471910112359553,
                        "keypointlabels": [
                            "right_hip"
                        ]
                    },
                    "from_name": "kp-1",
                    "to_name": "img-1",
                    "type": "keypointlabels",
                    "origin": "manual"
                },
                {
                    "original_width": 640,
                    "original_height": 360,
                    "image_rotation": 0,
                    "value": {
                        "x": 29.863972663879395,
                        "y": 50.27921040852864,
                        "width": 0.22471910112359553,
                        "keypointlabels": [
                            "left_knee"
                        ]
                    },
                    "from_name": "kp-1",
                    "to_name": "img-1",
                    "type": "keypointlabels",
                    "origin": "manual"
                },
                {
                    "original_width": 640,
                    "original_height": 360,
                    "image_rotation": 0,
                    "value": {
                        "x": 29.90832805633545,
                        "y": 48.98437923855251,
                        "width": 0.22471910112359553,
                        "keypointlabels": [
                            "right_knee"
                        ]
                    },
                    "from_name": "kp-1",
                    "to_name": "img-1",
                    "type": "keypointlabels",
                    "origin": "manual"
                },
                {
                    "original_width": 640,
                    "original_height": 360,
                    "image_rotation": 0,
                    "value": {
                        "x": 0.0,
                        "y": 0.0,
                        "width": 0.22471910112359553,
                        "keypointlabels": [
                            "left_ankle"
                        ]
                    },
                    "from_name": "kp-1",
                    "to_name": "img-1",
                    "type": "keypointlabels",
                    "origin": "manual"
                },
                {
                    "original_width": 640,
                    "original_height": 360,
                    "image_rotation": 0,
                    "value": {
                        "x": 0.0,
                        "y": 0.0,
                        "width": 0.22471910112359553,
                        "keypointlabels": [
                            "right_ankle"
                        ]
                    },
                    "from_name": "kp-1",
                    "to_name": "img-1",
                    "type": "keypointlabels",
                    "origin": "manual"
                },
                {
                    "original_width": 640,
                    "original_height": 360,
                    "image_rotation": 0,
                    "value": {
                        "x": 10.3125,
                        "y": 18.333333333333332,
                        "width": 24.375,
                        "height": 38.888888888888886,
                        "rectanglelabels": [
                            "People"
                        ]
                    },
                    "from_name": "label",
                    "to_name": "img-1",
                    "type": "rectanglelabels",
                    "origin": "manual"
                },
                {
                    "original_width": 640,
                    "original_height": 360,
                    "image_rotation": 0,
                    "value": {
                        "x": 0.0,
                        "y": 0.0,
                        "width": 0.22471910112359553,
                        "keypointlabels": [
                            "nose"
                        ]
                    },
                    "from_name": "kp-1",
                    "to_name": "img-1",
                    "type": "keypointlabels",
                    "origin": "manual"
                },
                {
                    "original_width": 640,
                    "original_height": 360,
                    "image_rotation": 0,
                    "value": {
                        "x": 34.537954330444336,
                        "y": 7.008981704711914,
                        "width": 0.22471910112359553,
                        "keypointlabels": [
                            "left_shoulder"
                        ]
                    },
                    "from_name": "kp-1",
                    "to_name": "img-1",
                    "type": "keypointlabels",
                    "origin": "manual"
                },
                {
                    "original_width": 640,
                    "original_height": 360,
                    "image_rotation": 0,
                    "value": {
                        "x": 32.79554605484009,
                        "y": 4.2683898078070746,
                        "width": 0.22471910112359553,
                        "keypointlabels": [
                            "right_shoulder"
                        ]
                    },
                    "from_name": "kp-1",
                    "to_name": "img-1",
                    "type": "keypointlabels",
                    "origin": "manual"
                },
                {
                    "original_width": 640,
                    "original_height": 360,
                    "image_rotation": 0,
                    "value": {
                        "x": 35.598177909851074,
                        "y": 14.137576421101887,
                        "width": 0.22471910112359553,
                        "keypointlabels": [
                            "left_elbow"
                        ]
                    },
                    "from_name": "kp-1",
                    "to_name": "img-1",
                    "type": "keypointlabels",
                    "origin": "manual"
                },
                {
                    "original_width": 640,
                    "original_height": 360,
                    "image_rotation": 0,
                    "value": {
                        "x": 29.43507671356201,
                        "y": 2.1420330471462674,
                        "width": 0.22471910112359553,
                        "keypointlabels": [
                            "right_elbow"
                        ]
                    },
                    "from_name": "kp-1",
                    "to_name": "img-1",
                    "type": "keypointlabels",
                    "origin": "manual"
                },
                {
                    "original_width": 640,
                    "original_height": 360,
                    "image_rotation": 0,
                    "value": {
                        "x": 32.3735237121582,
                        "y": 14.160265392727322,
                        "width": 0.22471910112359553,
                        "keypointlabels": [
                            "left_wrist"
                        ]
                    },
                    "from_name": "kp-1",
                    "to_name": "img-1",
                    "type": "keypointlabels",
                    "origin": "manual"
                },
                {
                    "original_width": 640,
                    "original_height": 360,
                    "image_rotation": 0,
                    "value": {
                        "x": 26.73257827758789,
                        "y": 0.7255416446261935,
                        "width": 0.22471910112359553,
                        "keypointlabels": [
                            "right_wrist"
                        ]
                    },
                    "from_name": "kp-1",
                    "to_name": "img-1",
                    "type": "keypointlabels",
                    "origin": "manual"
                },
                {
                    "original_width": 640,
                    "original_height": 360,
                    "image_rotation": 0,
                    "value": {
                        "x": 34.80579614639282,
                        "y": 18.680860731336804,
                        "width": 0.22471910112359553,
                        "keypointlabels": [
                            "left_hip"
                        ]
                    },
                    "from_name": "kp-1",
                    "to_name": "img-1",
                    "type": "keypointlabels",
                    "origin": "manual"
                },
                {
                    "original_width": 640,
                    "original_height": 360,
                    "image_rotation": 0,
                    "value": {
                        "x": 33.86878490447998,
                        "y": 17.795145246717663,
                        "width": 0.22471910112359553,
                        "keypointlabels": [
                            "right_hip"
                        ]
                    },
                    "from_name": "kp-1",
                    "to_name": "img-1",
                    "type": "keypointlabels",
                    "origin": "manual"
                },
                {
                    "original_width": 640,
                    "original_height": 360,
                    "image_rotation": 0,
                    "value": {
                        "x": 35.57877063751221,
                        "y": 26.822984483506943,
                        "width": 0.22471910112359553,
                        "keypointlabels": [
                            "left_knee"
                        ]
                    },
                    "from_name": "kp-1",
                    "to_name": "img-1",
                    "type": "keypointlabels",
                    "origin": "manual"
                },
                {
                    "original_width": 640,
                    "original_height": 360,
                    "image_rotation": 0,
                    "value": {
                        "x": 35.21487236022949,
                        "y": 26.23583051893446,
                        "width": 0.22471910112359553,
                        "keypointlabels": [
                            "right_knee"
                        ]
                    },
                    "from_name": "kp-1",
                    "to_name": "img-1",
                    "type": "keypointlabels",
                    "origin": "manual"
                },
                {
                    "original_width": 640,
                    "original_height": 360,
                    "image_rotation": 0,
                    "value": {
                        "x": 36.90565824508667,
                        "y": 34.076131184895836,
                        "width": 0.22471910112359553,
                        "keypointlabels": [
                            "left_ankle"
                        ]
                    },
                    "from_name": "kp-1",
                    "to_name": "img-1",
                    "type": "keypointlabels",
                    "origin": "manual"
                },
                {
                    "original_width": 640,
                    "original_height": 360,
                    "image_rotation": 0,
                    "value": {
                        "x": 36.747164726257324,
                        "y": 32.64002482096354,
                        "width": 0.22471910112359553,
                        "keypointlabels": [
                            "right_ankle"
                        ]
                    },
                    "from_name": "kp-1",
                    "to_name": "img-1",
                    "type": "keypointlabels",
                    "origin": "manual"
                },
                {
                    "original_width": 640,
                    "original_height": 360,
                    "image_rotation": 0,
                    "value": {
                        "x": 25.9375,
                        "y": 0.0,
                        "width": 12.1875,
                        "height": 38.05555555555556,
                        "rectanglelabels": [
                            "People"
                        ]
                    },
                    "from_name": "label",
                    "to_name": "img-1",
                    "type": "rectanglelabels",
                    "origin": "manual"
                }
            ]
        }
    ]
}
